{
  "note": {
    "noteId": "6a3b5d4d000000001702904c",
    "title": "🇵🇦Kent & Kristopher Lot 06 ASD日晒瑰夏",
    "desc": "🌸 香气描述 🫧\n\t\n闻豆时先是芒果、玉兰花、香草、蜜橘酸、西梅酸、核果酸与冲浪板同款樱桃酸，接着带出康科德葡萄、富士苹果、无花果、咖啡花、茉莉花与杏仁香，尾调落在牛奶香、蜜饯感、甜杏、血橙酸、柠檬蜜与奶油感；磨粉后先是茉莉花、玉兰花、木槿花、芒果与香水柠檬酸，随后浮现樱桃酸、苹果酸、树莓酸、丁香、肉桂、带皮橘子酸、核果酸与香水感；湿香阶段先是香水柠檬、核果酸、木槿花、咖啡花、苹果酸与葡萄柚酸，接着是葡萄酸、李子酸、金桔酸、啤梨、香草与奶油感，尾调收在白色香料、无花果、牛奶香与咖啡花茶\n\t\n-\n\t\n🎡 风味描述 🔮\n\t\n高温入口先是李子酸、啤梨、肉桂、血橙酸、苹果酸、香水柠檬、白色香料与优雅香气，啜吸时带出细腻核果香、茉莉花、咖啡花、牛奶香、蜜橘与杏仁香；中温时先是茉莉花、咖啡花、牛奶香、富士苹果、核果香与无花果，回味转为茉莉花茶、带皮蜜橘、芒果清香、柠檬马鞭草、奶油body与粉色花香；低温阶段整体很温柔，先是木槿花、咖啡花、茉莉花、肉桂、富士苹果与无花果，回味收在香水柠檬、紫葡萄、牛奶香、粉紫色花香、樱桃酸、核果香与柠檬马鞭草\n\t\n-\n\t\n🇨🇦 Rogue Wave | 🛖 Kent & Kristopher | ⛰️ 1650 m.a.s.l. | 📅 2026.05.20 | 🫘 瑰夏 | 🌞 ASD日晒 | 📝 李子/康科德葡萄/芒果/茉莉花/香水柠檬\n\t\n⏳ v60 | 📄 Origami漂白 | ⚙️ C40 #23[话题]# | 🌡️ 94°C | 🪨 90ppm | 🫘 16g | 💧 90🔄🥄/70🔄/70🔄📍/40📍🌪️ | ⏰ 3m50s\n\t\n-\n\t\n#手冲咖啡[话题]# #精品咖啡[话题]# #咖啡豆[话题]# #我的咖啡日记[话题]# #咖啡日常[话题]# #咖啡与生活[话题]# #咖啡风味轮[话题]# #今天你喝咖啡了吗[话题]# #巴拿马[话题]# #瑰夏[话题]# #巴拿马瑰夏[话题]# #Kent&Kristopher[话题]# #Lamastus[话题]# #RogueWave[话题]#",
    "body": "🌸 香气描述 🫧\n\t\n闻豆时先是芒果、玉兰花、香草、蜜橘酸、西梅酸、核果酸与冲浪板同款樱桃酸，接着带出康科德葡萄、富士苹果、无花果、咖啡花、茉莉花与杏仁香，尾调落在牛奶香、蜜饯感、甜杏、血橙酸、柠檬蜜与奶油感；磨粉后先是茉莉花、玉兰花、木槿花、芒果与香水柠檬酸，随后浮现樱桃酸、苹果酸、树莓酸、丁香、肉桂、带皮橘子酸、核果酸与香水感；湿香阶段先是香水柠檬、核果酸、木槿花、咖啡花、苹果酸与葡萄柚酸，接着是葡萄酸、李子酸、金桔酸、啤梨、香草与奶油感，尾调收在白色香料、无花果、牛奶香与咖啡花茶\n\t\n-\n\t\n🎡 风味描述 🔮\n\t\n高温入口先是李子酸、啤梨、肉桂、血橙酸、苹果酸、香水柠檬、白色香料与优雅香气，啜吸时带出细腻核果香、茉莉花、咖啡花、牛奶香、蜜橘与杏仁香；中温时先是茉莉花、咖啡花、牛奶香、富士苹果、核果香与无花果，回味转为茉莉花茶、带皮蜜橘、芒果清香、柠檬马鞭草、奶油body与粉色花香；低温阶段整体很温柔，先是木槿花、咖啡花、茉莉花、肉桂、富士苹果与无花果，回味收在香水柠檬、紫葡萄、牛奶香、粉紫色花香、樱桃酸、核果香与柠檬马鞭草\n\t\n-\n\t\n🇨🇦 Rogue Wave | 🛖 Kent & Kristopher | ⛰️ 1650 m.a.s.l. | 📅 2026.05.20 | 🫘 瑰夏 | 🌞 ASD日晒 | 📝 李子/康科德葡萄/芒果/茉莉花/香水柠檬\n\t\n⏳ v60 | 📄 Origami漂白 | ⚙️ C40  | 🌡️ 94°C | 🪨 90ppm | 🫘 16g | 💧 90🔄🥄/70🔄/70🔄📍/40📍🌪️ | ⏰ 3m50s\n\t\n-\n\t\n           Kent&Kristopher",
    "tags": [
      "#23",
      "#手冲咖啡",
      "#精品咖啡",
      "#咖啡豆",
      "#我的咖啡日记",
      "#咖啡日常",
      "#咖啡与生活",
      "#咖啡风味轮",
      "#今天你喝咖啡了吗",
      "#巴拿马",
      "#瑰夏",
      "#巴拿马瑰夏",
      "#Lamastus",
      "#RogueWave"
    ],
    "type": "normal",
    "time": 1782275405000,
    "ipLocation": "北京",
    "user": {
      "userId": "5b0e3acd4eacab39121875b2",
      "nickname": "做作的Morpheus"
    },
    "interactInfo": {
      "liked": false,
      "likedCount": "12",
      "collectedCount": "1",
      "collected": false,
      "commentCount": "1",
      "sharedCount": ""
    },
    "imageList": [
      {
        "width": 1086,
        "height": 1448,
        "urlDefault": "http://sns-webpic-qc.xhscdn.com/202606302146/b8e70fd9153093254202a25b6e2b755c/notes_pre_post/1040g3k8321pla6finke04a5paetcqtdiqgbn328!nd_dft_wlteh_webp_3"
      },
      {
        "width": 1086,
        "height": 1448,
        "urlDefault": "http://sns-webpic-qc.xhscdn.com/202606302146/4ea48c19e7372178c64a18c41a22d4a1/notes_pre_post/1040g3k8321pla6finkeg4a5paetcqtdikve6t70!nd_dft_wlteh_webp_3"
      },
      {
        "width": 3464,
        "height": 4618,
        "urlDefault": "http://sns-webpic-qc.xhscdn.com/202606302146/de3af55914d15f72287c0d1dd281a527/notes_pre_post/1040g3k8321pla6finkf04a5paetcqtdii1go0o0!nd_dft_wlteh_webp_3"
      },
      {
        "width": 3110,
        "height": 4147,
        "urlDefault": "http://sns-webpic-qc.xhscdn.com/202606302146/4b4d0357003a8d5587a1c81f4dc18ede/notes_pre_post/1040g3k8321pla6finkfg4a5paetcqtdiufq0d20!nd_dft_wlteh_webp_3"
      },
      {
        "width": 3186,
        "height": 4249,
        "urlDefault": "http://sns-webpic-qc.xhscdn.com/202606302146/49886b33676599df65fc7b0b074b426b/notes_pre_post/1040g3k8321pla6finkg04a5paetcqtditdeiif0!nd_dft_wlteh_webp_3"
      },
      {
        "width": 3020,
        "height": 4027,
        "urlDefault": "http://sns-webpic-qc.xhscdn.com/202606302146/64810ca433de49cfa5b66033c9a4a508/notes_pre_post/1040g3k8321pla6finkgg4a5paetcqtdic9491t8!nd_dft_wlteh_webp_3"
      },
      {
        "width": 3530,
        "height": 4709,
        "urlDefault": "http://sns-webpic-qc.xhscdn.com/202606302146/172999ee0f7289e8009e549404bce842/notes_pre_post/1040g3k8321pla6finkh04a5paetcqtdigkaq7t0!nd_dft_wlteh_webp_3"
      }
    ]
  },
  "comments": [
    {
      "id": "6a3b5d57000000001403be3a",
      "content": "【冲煮方案】\n水质：怡宝+Apax+TWW 90ppm\n滤杯：v60\n滤纸：Origami漂白\n研磨度：C40 23# 中度研磨\n粉水比：1:16.9\n\n【冲煮参数】\n16g粉，270g注水，约3:50撤杯\n0:00-0:09：90g/94°C，绕圈注水，闷蒸，搅拌\n0:35-0:55：160g(+70g)/94°C，绕圈注水\n1:15-1:22：230g(+70g)/94°C，扫粉后中心注水\n1:33-1:36：270g(+40g)/94°C，中心注水，摇晃",
      "likeCount": "0",
      "createTime": 1782275415000,
      "ipLocation": "北京",
      "user": {
        "userId": "5b0e3acd4eacab39121875b2",
        "nickname": "做作的Morpheus"
      },
      "subCommentCount": "0"
    }
  ]
}
