{
  "note": {
    "noteId": "6a1f0cc4000000003701ee4b",
    "title": "🇪🇹埃塞瑰夏村Oma #109水洗瑰夏1931",
    "desc": "🌸 香气描述 🫧\n\t\n闻豆时先是茉莉花、栀子花、牡丹花、山茶花与金银花铺开，接着带出荔枝、白桃、丁香、葡萄、咖啡果肉与苹果香，再往后是甜橙、铃兰、焦糖、带皮柚子酸、黄柠檬、咖啡花与牛奶香，尾调落在具象白茶、橙子酸、蜜柑、具象杏桃、金银花、粉色花香与蜂蜜感；磨粉后先是水蜜桃、蜜橘、甜橙、栀子花、铃兰、牡丹、柚子酸与清幽茶香，随后浮现橙子汽水、橙子果肉、咖啡花、具象茉莉花、柠檬草、白色果肉、花蜜香与核果甜，尾调转为苹果香、香草、ttms橙子糖、甜杏、荔枝、白葡萄、菊花茶与细腻花草茶；湿香阶段先是杏桃、咖啡花、黄柠檬、牡丹、苹果酸与玉露茶，接着是栀子花、茉莉花、香草、铃兰、玉兰花与荔枝白茶，尾调收在浓郁白色花香、咖啡果肉、具象甜橙与具象核果香，同时还有白葡萄、蜜瓜、桃子汽水、鲜鸡汤与奶油感\n\t\n-\n\t\n🎡 风味描述 🔮\n\t\n高温入口先是黄柠檬酸、白桃、丁香、咖啡花、杏子酸与具象苹果酸，啜吸时带出茉莉花、金银花、牡丹花、带皮甜橙与蜜橘酸，回味落在栀子花、具象柠檬香、柠檬糖、橘子汽水与花草茶；中温时先是蜜橘酸、苹果酸、柠檬酸、杏桃酸、柠檬草与花草茶，回味转为核果香、香草、咖啡花、铃兰、甜橙、玉露茶与奶油感；低温阶段先是丁香、白桃、甜橙、白茶、苹果酸与柠檬酸，随后浮现金银花、牡丹花、铃兰露水感、咖啡花、白色果肉与风土感，回味收在荔枝、杏桃酸、柠檬草、蜜橘酸、青柠酸、具象甜橙与橙子汽水\n\t\n-\n\t\n🇨🇳 kw自在心 | 🛖 Gesha Village - Oma | ⛰️ 1931-2040 m.a.s.l. | 📅 2026.05.13 | 🫘 瑰夏1931 | 💧 水洗 | 📝 茉莉花/牡丹/甜橙/金银花\n\t\n⏳ Brewista | 📄 Origami 155 | ⚙️ C40 #24[话题]# | 🌡️ 93°C | 🪨 90ppm | 🫘 15g | 💧 50🔄🌪️/100🔄/90🔄📍🌪️ | ⏰ 2m30s\n\t\n-\n\t\n#手冲咖啡[话题]# #精品咖啡[话题]# #咖啡豆[话题]# #我的咖啡日记[话题]# #咖啡日常[话题]# #咖啡与生活[话题]# #咖啡风味轮[话题]# #今天你喝咖啡了吗[话题]# #埃塞俄比亚[话题]# #瑰夏[话题]# #瑰夏村[话题]# #金标瑰夏[话题]# #Oma[话题]# #kw自在心[话题]#",
    "body": "🌸 香气描述 🫧\n\t\n闻豆时先是茉莉花、栀子花、牡丹花、山茶花与金银花铺开，接着带出荔枝、白桃、丁香、葡萄、咖啡果肉与苹果香，再往后是甜橙、铃兰、焦糖、带皮柚子酸、黄柠檬、咖啡花与牛奶香，尾调落在具象白茶、橙子酸、蜜柑、具象杏桃、金银花、粉色花香与蜂蜜感；磨粉后先是水蜜桃、蜜橘、甜橙、栀子花、铃兰、牡丹、柚子酸与清幽茶香，随后浮现橙子汽水、橙子果肉、咖啡花、具象茉莉花、柠檬草、白色果肉、花蜜香与核果甜，尾调转为苹果香、香草、ttms橙子糖、甜杏、荔枝、白葡萄、菊花茶与细腻花草茶；湿香阶段先是杏桃、咖啡花、黄柠檬、牡丹、苹果酸与玉露茶，接着是栀子花、茉莉花、香草、铃兰、玉兰花与荔枝白茶，尾调收在浓郁白色花香、咖啡果肉、具象甜橙与具象核果香，同时还有白葡萄、蜜瓜、桃子汽水、鲜鸡汤与奶油感\n\t\n-\n\t\n🎡 风味描述 🔮\n\t\n高温入口先是黄柠檬酸、白桃、丁香、咖啡花、杏子酸与具象苹果酸，啜吸时带出茉莉花、金银花、牡丹花、带皮甜橙与蜜橘酸，回味落在栀子花、具象柠檬香、柠檬糖、橘子汽水与花草茶；中温时先是蜜橘酸、苹果酸、柠檬酸、杏桃酸、柠檬草与花草茶，回味转为核果香、香草、咖啡花、铃兰、甜橙、玉露茶与奶油感；低温阶段先是丁香、白桃、甜橙、白茶、苹果酸与柠檬酸，随后浮现金银花、牡丹花、铃兰露水感、咖啡花、白色果肉与风土感，回味收在荔枝、杏桃酸、柠檬草、蜜橘酸、青柠酸、具象甜橙与橙子汽水\n\t\n-\n\t\n🇨🇳 kw自在心 | 🛖 Gesha Village - Oma | ⛰️ 1931-2040 m.a.s.l. | 📅 2026.05.13 | 🫘 瑰夏1931 | 💧 水洗 | 📝 茉莉花/牡丹/甜橙/金银花\n\t\n⏳ Brewista | 📄 Origami 155 | ⚙️ C40  | 🌡️ 93°C | 🪨 90ppm | 🫘 15g | 💧 50🔄🌪️/100🔄/90🔄📍🌪️ | ⏰ 2m30s\n\t\n-",
    "tags": [
      "#24",
      "#手冲咖啡",
      "#精品咖啡",
      "#咖啡豆",
      "#我的咖啡日记",
      "#咖啡日常",
      "#咖啡与生活",
      "#咖啡风味轮",
      "#今天你喝咖啡了吗",
      "#埃塞俄比亚",
      "#瑰夏",
      "#瑰夏村",
      "#金标瑰夏",
      "#Oma",
      "#kw自在心"
    ],
    "type": "normal",
    "time": 1780448521000,
    "ipLocation": "北京",
    "user": {
      "userId": "5b0e3acd4eacab39121875b2",
      "nickname": "做作的Morpheus"
    },
    "interactInfo": {
      "liked": false,
      "likedCount": "23",
      "collectedCount": "6",
      "collected": false,
      "commentCount": "2",
      "sharedCount": ""
    },
    "imageList": [
      {
        "width": 3464,
        "height": 4618,
        "urlDefault": "http://sns-webpic-qc.xhscdn.com/202606302157/9ddd3ab0f8e74a4a2c44aafb85673af8/notes_pre_post/1040g3k0320u0gahano004a5paetcqtdie5unt68!nd_dft_wlteh_webp_3"
      },
      {
        "width": 1086,
        "height": 1448,
        "urlDefault": "http://sns-webpic-qc.xhscdn.com/202606302157/3862ddb51ab315641f1af6900b901640/notes_pre_post/1040g3k0320u0gahano0g4a5paetcqtdiqtaqpl0!nd_dft_wlteh_webp_3"
      },
      {
        "width": 1086,
        "height": 1448,
        "urlDefault": "http://sns-webpic-qc.xhscdn.com/202606302157/70e1d168f7f5f8b8a2df30edc7166412/notes_pre_post/1040g3k0320u0gahano104a5paetcqtdilad8m48!nd_dft_wlteh_webp_3"
      },
      {
        "width": 3289,
        "height": 4386,
        "urlDefault": "http://sns-webpic-qc.xhscdn.com/202606302157/78566151ff9d152209abebef1bed0a3d/notes_pre_post/1040g3k0320u0gahano1g4a5paetcqtdij1g0rco!nd_dft_wlteh_webp_3"
      },
      {
        "width": 3060,
        "height": 4080,
        "urlDefault": "http://sns-webpic-qc.xhscdn.com/202606302157/98eeded0e316b63a391cfd40c94cf942/notes_pre_post/1040g3k0320u0gahano204a5paetcqtdi434b43o!nd_dft_wlteh_webp_3"
      },
      {
        "width": 2909,
        "height": 3879,
        "urlDefault": "http://sns-webpic-qc.xhscdn.com/202606302157/76c9a958c4327c60f2a7fc1118fdc904/notes_pre_post/1040g3k0320u0gahano2g4a5paetcqtdiq6uunl0!nd_dft_wlteh_webp_3"
      },
      {
        "width": 3590,
        "height": 4787,
        "urlDefault": "http://sns-webpic-qc.xhscdn.com/202606302157/2da5635529344007e375bcf5a88007c5/notes_pre_post/1040g3k0320u0gahano304a5paetcqtdi5ab8hq8!nd_dft_wlteh_webp_3"
      }
    ]
  },
  "comments": [
    {
      "id": "6a1f9aab000000002a02ef38",
      "content": "鲜鸡汤与奶油感\n感觉能喝饱饱",
      "likeCount": "1",
      "createTime": 1780456107000,
      "ipLocation": "广东",
      "user": {
        "userId": "5b28ef71e8ac2b7caca99b6f",
        "nickname": "Apple"
      },
      "subCommentCount": "0"
    },
    {
      "id": "6a1f810700000000280364f6",
      "content": "[派对R][派对R][派对R][派对R][派对R]",
      "likeCount": "1",
      "createTime": 1780449543000,
      "ipLocation": "广东",
      "user": {
        "userId": "59f805a64eacab7536580d6a",
        "nickname": "💍GraceLoveMt.Totumas"
      },
      "subCommentCount": "0"
    }
  ]
}
