{
  "note": {
    "noteId": "6a39474400000000060322bd",
    "title": "YELEI 翡翠红标 日晒 Guabo 4NC",
    "desc": "香气强度很高，果酱感，以为是tumaco系酸p咖啡，联想到国产黄樱桃；入口柑橘调酸甜，没有樱桃那么酸，平衡感不错；高温body偏弱，中温还行，有点包裹感了\n#我的咖啡日记[话题]# #手冲咖啡[话题]#",
    "body": "香气强度很高，果酱感，以为是tumaco系酸p咖啡，联想到国产黄樱桃；入口柑橘调酸甜，没有樱桃那么酸，平衡感不错；高温body偏弱，中温还行，有点包裹感了",
    "tags": [
      "#我的咖啡日记",
      "#手冲咖啡"
    ],
    "type": "normal",
    "time": 1782138692000,
    "ipLocation": "北京",
    "user": {
      "userId": "614f3653000000001f03e24b",
      "nickname": "柑橘科科长"
    },
    "interactInfo": {
      "liked": false,
      "likedCount": "16",
      "collectedCount": "1",
      "collected": false,
      "commentCount": "0",
      "sharedCount": ""
    },
    "imageList": [
      {
        "width": 1918,
        "height": 2560,
        "urlDefault": "http://sns-webpic-qc.xhscdn.com/202606302146/487946bbe3cf048c22feff3f898eae5a/notes_uhdr/1040g3qo321nk65stnee05oaf6p9nvoibkem1r38!nd_dft_wlteh_webp_3"
      }
    ]
  },
  "comments": []
}
