{
  "note": {
    "noteId": "68f4b2c7000000000500143b",
    "title": "oma Totumas mosto水洗",
    "desc": "好喝，具象的柚子，老师指导得好[赞R]\n#我的咖啡日记[话题]# #手冲咖啡[话题]#",
    "body": "好喝，具象的柚子，老师指导得好",
    "tags": [
      "#我的咖啡日记",
      "#手冲咖啡"
    ],
    "type": "normal",
    "time": 1760867015000,
    "ipLocation": "",
    "user": {
      "userId": "614f3653000000001f03e24b",
      "nickname": "柑橘科科长"
    },
    "interactInfo": {
      "liked": false,
      "likedCount": "11",
      "collectedCount": "0",
      "collected": false,
      "commentCount": "3",
      "sharedCount": ""
    },
    "imageList": [
      {
        "width": 2560,
        "height": 1804,
        "urlDefault": "http://sns-webpic-qc.xhscdn.com/202606302228/bb49ae6ff512eb63b7d4544862e4708d/notes_pre_post/1040g3k031nqksv91lm005oaf6p9nvoibr5i10ko!nd_dft_wgth_webp_3"
      }
    ]
  },
  "comments": [
    {
      "id": "68f4b86b000000003702576e",
      "content": "oma的托托马斯据说很顶[doge]",
      "likeCount": "1",
      "createTime": 1760868459000,
      "ipLocation": "福建",
      "user": {
        "userId": "58fe12675e87e72145e892a7",
        "nickname": "L.N"
      },
      "subCommentCount": "1",
      "subComments": [
        {
          "id": "68f4b881000000003802684a",
          "content": "这支不错 森林日晒不太行",
          "likeCount": "0",
          "createTime": 1760868481000,
          "ipLocation": "云南",
          "user": {
            "userId": "614f3653000000001f03e24b",
            "nickname": "柑橘科科长"
          },
          "subCommentCount": ""
        }
      ]
    },
    {
      "id": "68f4c53c000000003803f331",
      "content": "羡慕",
      "likeCount": "0",
      "createTime": 1760871741000,
      "ipLocation": "广东",
      "user": {
        "userId": "5d69466d000000000100ae9f",
        "nickname": "咖啡岛的收件箱"
      },
      "subCommentCount": "0"
    }
  ]
}
