{
  "note": {
    "noteId": "65e40ba70000000003034c79",
    "title": "CoffeeTech 小庄园水洗Lot D",
    "desc": "杀死比赛！本季度最强水洗！[赞R][赞R][赞R]\n还没磨开粉就已经有很强烈的橙花香，磨开粉后直冲天灵盖[派对R]\n在冲煮的时候已经表现出很复杂的香气，分段冲煮，每一段都有极具辨识度的香气，从橙花到蜜桃到焦糖，拿开滤杯后扑面而来的香气[大笑R]\n入口是丝绒般光滑的触感🦢，前段呈现出蜜桃🍑，太妃糖🍬的风味，后段酸度上升，转化成苹果🍎，柑橘🍊，最喜欢它的余韵，口腔里残留着烤吐司的甜香味🍞，极度优雅，物远超所值[哇R]不得不感叹，真的顶级这小庄园，喝一次震撼我一次[惊恐R]\n#手冲咖啡[话题]# #我的咖啡日记[话题]# #每一天都很哇塞[话题]#",
    "body": "杀死比赛！本季度最强水洗！\n还没磨开粉就已经有很强烈的橙花香，磨开粉后直冲天灵盖\n在冲煮的时候已经表现出很复杂的香气，分段冲煮，每一段都有极具辨识度的香气，从橙花到蜜桃到焦糖，拿开滤杯后扑面而来的香气\n入口是丝绒般光滑的触感🦢，前段呈现出蜜桃🍑，太妃糖🍬的风味，后段酸度上升，转化成苹果🍎，柑橘🍊，最喜欢它的余韵，口腔里残留着烤吐司的甜香味🍞，极度优雅，物远超所值不得不感叹，真的顶级这小庄园，喝一次震撼我一次",
    "tags": [
      "#手冲咖啡",
      "#我的咖啡日记",
      "#每一天都很哇塞"
    ],
    "type": "normal",
    "time": 1709444008000,
    "ipLocation": "",
    "user": {
      "userId": "614f3653000000001f03e24b",
      "nickname": "柑橘科科长"
    },
    "interactInfo": {
      "liked": false,
      "likedCount": "6",
      "collectedCount": "0",
      "collected": false,
      "commentCount": "1",
      "sharedCount": ""
    },
    "imageList": [
      {
        "width": 2560,
        "height": 1920,
        "urlDefault": "http://sns-webpic-qc.xhscdn.com/202607010000/b9e593b1dc6ca96fa1a0868298bdc94b/1040g2sg30vsclber5o005oaf6p9nvoibi3uhmp8!nd_dft_wgth_webp_3"
      }
    ]
  },
  "comments": [
    {
      "id": "661b23f7000000001b039918",
      "content": "很oi",
      "likeCount": "0",
      "createTime": 1713054713000,
      "ipLocation": "福建",
      "user": {
        "userId": "5d3c1465000000001001b176",
        "nickname": "Kerwin"
      },
      "subCommentCount": "0"
    }
  ]
}
