{
  "note": {
    "noteId": "6a27b7f2000000002102281a",
    "title": "柠檬山竹乌龙茶-Joe豆翡翠红标Durazno水洗",
    "desc": "豆子：巴拿马-翡翠庄园-红标Durazno 4FB-瑰夏-水洗 from Joe Coffee\n\\\n器具：Origami，司令官C40，C壶\n参数：C40-24格，15.5g粉，粉水比约1:15，水温92摄氏度。\n冲煮：跷跷板三段式：30ml水预浸35s，第二段小水柱缓慢中心注水至240ml，2:02结束萃取。\n/\n☕️感谢程局投喂的Joe豆新产季翡翠红标，打开管子就能闻到非常香甜的气息。冲煮节奏没控制好，偏慢了一些，整个萃取有点过头，失误了，不过也还好没完全掩盖豆子的优点。\n🧃高温会比较偏红茶和黄糖，随着温度降下来，白色花香会逐渐明显，明亮水果的调性也随之提升，柠檬、山竹和酸橘子的感觉，然后会有因为时间拖长导致的乌龙茶感。\n#浪漫生活的记录者[话题]# #咖啡豆推荐[话题]# #MonsieurBanane促产[话题]# #COTD咖啡探店[话题]# #精品咖啡[话题]# #我的咖啡日记[话题]# #手冲咖啡[话题]# #瑰夏[话题]# #翡翠庄园[话题]# #好味咖啡豆[话题]#",
    "body": "豆子：巴拿马-翡翠庄园-红标Durazno 4FB-瑰夏-水洗 from Joe Coffee\n\\\n器具：Origami，司令官C40，C壶\n参数：C40-24格，15.5g粉，粉水比约1:15，水温92摄氏度。\n冲煮：跷跷板三段式：30ml水预浸35s，第二段小水柱缓慢中心注水至240ml，2:02结束萃取。\n/\n☕️感谢程局投喂的Joe豆新产季翡翠红标，打开管子就能闻到非常香甜的气息。冲煮节奏没控制好，偏慢了一些，整个萃取有点过头，失误了，不过也还好没完全掩盖豆子的优点。\n🧃高温会比较偏红茶和黄糖，随着温度降下来，白色花香会逐渐明显，明亮水果的调性也随之提升，柠檬、山竹和酸橘子的感觉，然后会有因为时间拖长导致的乌龙茶感。",
    "tags": [
      "#浪漫生活的记录者",
      "#咖啡豆推荐",
      "#MonsieurBanane促产",
      "#COTD咖啡探店",
      "#精品咖啡",
      "#我的咖啡日记",
      "#手冲咖啡",
      "#瑰夏",
      "#翡翠庄园",
      "#好味咖啡豆"
    ],
    "type": "normal",
    "time": 1780987890000,
    "ipLocation": "湖南",
    "user": {
      "userId": "604eefdd0000000001002980",
      "nickname": "斯慕吉Smoothie"
    },
    "interactInfo": {
      "liked": false,
      "likedCount": "18",
      "collectedCount": "",
      "collected": false,
      "commentCount": "2",
      "sharedCount": ""
    },
    "imageList": [
      {
        "width": 4258,
        "height": 5509,
        "urlDefault": "http://sns-webpic-qc.xhscdn.com/202606302156/d1ce8cfb9d8fa72fc94f13a1c48e823a/note_pre_post_uhdr/1040g3r03216fckvenk005o2etveg8ac07smnb8o!nd_dft_wlteh_webp_3"
      },
      {
        "width": 1536,
        "height": 2530,
        "urlDefault": "http://sns-webpic-qc.xhscdn.com/202606302156/7cb340a66fc6f6f8d8de420d48c36857/notes_pre_post/1040g3k03216f8h2j7u005o2etveg8ac0ukfc2c8!nd_dft_wlteh_webp_3"
      }
    ]
  },
  "comments": [
    {
      "id": "6a2aac2a000000002900c8ec",
      "content": "这包装有点可爱诶",
      "likeCount": "0",
      "createTime": 1781181482000,
      "ipLocation": "湖南",
      "user": {
        "userId": "5cdcbc8000000000100379ad",
        "nickname": "一半的Lucky"
      },
      "subCommentCount": "1",
      "subComments": [
        {
          "id": "6a2b6ec7000000002a03271e",
          "content": "小小一管[偷笑R][偷笑R]",
          "likeCount": "0",
          "createTime": 1781231303000,
          "ipLocation": "湖南",
          "user": {
            "userId": "604eefdd0000000001002980",
            "nickname": "斯慕吉Smoothie"
          },
          "subCommentCount": ""
        }
      ]
    }
  ]
}
