{
  "note": {
    "noteId": "683d4fec0000000022005560",
    "title": "2025巴拿马黛博拉庄园传统日晒Afterglow",
    "desc": "豆子：巴拿马-黛博拉庄园-Afterglow晚霞-瑰夏-传统日晒 from KW自在心\n器具：origami，司令官C40，C壶\n参数：C40-27格，15g粉，粉水比约1:14，水温93摄氏度。\n冲煮：高浓低萃三段式：30ml水焖蒸30s，下一段绕圈注水至140ml，最后一段中心注水至210ml，1:49结束萃取。\n前嗅觉：橙花、菠萝、黄桃\n后嗅觉：菠萝、芒果硬糖、橘子\n味觉：菠萝酸质、水果糖甜\n触感：高黏稠度、中等重量果汁感\n色彩：Ral 冰果汁黄\n这只Afterglow喝起来整体感觉和Vivid有些许类似，只不过完完全全就是日晒的色彩了。不过整体调性和风味强度表现个人感觉比Vivid稍微差点意思，甜度倒是更高，黏稠度也更高，但是显得欠缺了Vivid那种新鲜多汁的口感，要更沾粘沉闷。风味呈现上完全就是黄色水果，菠萝的酸质还是很不错的，芒果硬糖般的甜感，橘子和黄桃的调性感受有点被厚重的甜压制，香气不够清晰上扬，当然这些都是对比前一只Vivid来的，单独来评价这只Afterglow还是很不错的。\n#夏日消暑风味集[话题]# #精品咖啡[话题]# #手冲咖啡[话题]# #COTD咖啡探店[话题]# #我的咖啡日记[话题]# #咖啡豆推荐[话题]# #瑰夏[话题]# #生活美学[话题]# #手冲咖啡日常[话题]# #长沙咖啡店[话题]#",
    "body": "豆子：巴拿马-黛博拉庄园-Afterglow晚霞-瑰夏-传统日晒 from KW自在心\n器具：origami，司令官C40，C壶\n参数：C40-27格，15g粉，粉水比约1:14，水温93摄氏度。\n冲煮：高浓低萃三段式：30ml水焖蒸30s，下一段绕圈注水至140ml，最后一段中心注水至210ml，1:49结束萃取。\n前嗅觉：橙花、菠萝、黄桃\n后嗅觉：菠萝、芒果硬糖、橘子\n味觉：菠萝酸质、水果糖甜\n触感：高黏稠度、中等重量果汁感\n色彩：Ral 冰果汁黄\n这只Afterglow喝起来整体感觉和Vivid有些许类似，只不过完完全全就是日晒的色彩了。不过整体调性和风味强度表现个人感觉比Vivid稍微差点意思，甜度倒是更高，黏稠度也更高，但是显得欠缺了Vivid那种新鲜多汁的口感，要更沾粘沉闷。风味呈现上完全就是黄色水果，菠萝的酸质还是很不错的，芒果硬糖般的甜感，橘子和黄桃的调性感受有点被厚重的甜压制，香气不够清晰上扬，当然这些都是对比前一只Vivid来的，单独来评价这只Afterglow还是很不错的。",
    "tags": [
      "#夏日消暑风味集",
      "#精品咖啡",
      "#手冲咖啡",
      "#COTD咖啡探店",
      "#我的咖啡日记",
      "#咖啡豆推荐",
      "#瑰夏",
      "#生活美学",
      "#手冲咖啡日常",
      "#长沙咖啡店"
    ],
    "type": "normal",
    "time": 1748848620000,
    "ipLocation": "",
    "user": {
      "userId": "604eefdd0000000001002980",
      "nickname": "斯慕吉Smoothie"
    },
    "interactInfo": {
      "liked": true,
      "likedCount": "17",
      "collectedCount": "1",
      "collected": false,
      "commentCount": "9",
      "sharedCount": ""
    },
    "imageList": [
      {
        "width": 3389,
        "height": 5231,
        "urlDefault": "http://sns-webpic-qc.xhscdn.com/202606302324/8a16ed50b93f57e0c7c4f7ae8aaa7aed/notes_pre_post/1040g3k831i7i7avsne705o2etveg8ac0so7bhoo!nd_dft_wlteh_webp_3"
      },
      {
        "width": 1179,
        "height": 2013,
        "urlDefault": "http://sns-webpic-qc.xhscdn.com/202606302324/acd37c855c717dced85eb5aa9ac0ea89/notes_pre_post/1040g3k831i7i7avsne7g5o2etveg8ac0ofuce5o!nd_dft_wlteh_webp_3"
      }
    ]
  },
  "comments": [
    {
      "id": "684041f6000000000a0359a9",
      "content": "粘稠的果汁，爱了[哇R]",
      "likeCount": "0",
      "createTime": 1749041654000,
      "ipLocation": "广东",
      "user": {
        "userId": "57bb058f6a6a69659e6660d1",
        "nickname": "阿柴五柴"
      },
      "subCommentCount": "1",
      "subComments": [
        {
          "id": "68404aaa000000000b02f4d8",
          "content": "[喝奶茶R][喝奶茶R][喝奶茶R]",
          "likeCount": "0",
          "createTime": 1749043882000,
          "ipLocation": "江西",
          "user": {
            "userId": "604eefdd0000000001002980",
            "nickname": "斯慕吉Smoothie"
          },
          "subCommentCount": ""
        }
      ]
    },
    {
      "id": "683d5f06000000000b015daf",
      "content": "好爆炸的热带水果！咖雅花也雅[看R][哇R]",
      "likeCount": "0",
      "createTime": 1748852486000,
      "ipLocation": "江苏",
      "user": {
        "userId": "5f5866bd000000000100a199",
        "nickname": "陈铁柱Jocelyn"
      },
      "subCommentCount": "1",
      "subComments": [
        {
          "id": "683d6021000000000b02e73c",
          "content": "诶嘿嘿[暗中观察R][暗中观察R]",
          "likeCount": "0",
          "createTime": 1748852770000,
          "ipLocation": "湖南",
          "user": {
            "userId": "604eefdd0000000001002980",
            "nickname": "斯慕吉Smoothie"
          },
          "subCommentCount": ""
        }
      ]
    },
    {
      "id": "683d527e000000001c017cdb",
      "content": "看成马黛茶🧉[斜眼R]",
      "likeCount": "0",
      "createTime": 1748849279000,
      "ipLocation": "广东",
      "user": {
        "userId": "5657a5dc6a6a692daec52e31",
        "nickname": "冷漠的🍍🐔"
      },
      "subCommentCount": "1",
      "subComments": [
        {
          "id": "683d52e300000000030355db",
          "content": "",
          "likeCount": "0",
          "createTime": 1748849380000,
          "ipLocation": "湖南",
          "user": {
            "userId": "604eefdd0000000001002980",
            "nickname": "斯慕吉Smoothie"
          },
          "subCommentCount": ""
        }
      ]
    },
    {
      "id": "683d50e8000000001c029146",
      "content": "[色色R][色色R][色色R]",
      "likeCount": "0",
      "createTime": 1748848873000,
      "ipLocation": "云南",
      "user": {
        "userId": "569a1f8e4775a76bb4ab65d9",
        "nickname": "打火机与公主裙-"
      },
      "subCommentCount": "0"
    },
    {
      "id": "683d7f66000000000a035b68",
      "content": "[赞R][赞R][赞R]",
      "likeCount": "0",
      "createTime": 1748860775000,
      "ipLocation": "广东",
      "user": {
        "userId": "665a7c86000000000700434e",
        "nickname": "KW自在心精品咖啡"
      },
      "subCommentCount": "1",
      "subComments": [
        {
          "id": "683d8947000000000a03777f",
          "content": "[喝奶茶R][喝奶茶R][喝奶茶R]",
          "likeCount": "0",
          "createTime": 1748863303000,
          "ipLocation": "湖南",
          "user": {
            "userId": "604eefdd0000000001002980",
            "nickname": "斯慕吉Smoothie"
          },
          "subCommentCount": ""
        }
      ]
    }
  ]
}
