{
  "note": {
    "noteId": "67f267c6000000001b039bfc",
    "title": "CC巴拿马阿尔铁里庄园Chombi水洗瑰夏",
    "desc": "豆子：巴拿马-阿尔铁里庄园-Chombi-瑰夏-水洗 from Coffea Circulor\n器具：origami，司令官C40，C壶\n参数：C40-25格，20g粉，粉水比约1:15，水温93摄氏度。\n冲煮：Amis搅拌法：120ml水搅拌焖蒸，25s搅拌，30s静置，下一段松屋式打水至150ml，转中心注水，最后一段大绕圈注至300ml，搅拌，截流，1:58结束萃取，24ml水bypass。\n前嗅觉：高强度花香，有带暖意的甜感，干净度高，浅浅的糖果调，无杂味。\n口感：酸质明亮强度高，甜度具象强度中低，酸更有存在感，黏稠度和重量感都较低，丝滑柔顺，无苦无糙涩。\n后嗅觉：风味强度中高，清晰度不错，甜感强度不算突出，但也容易感知，香气很饱满，经典水洗味，无杂味。\n尾韵：尾韵花果香韧性都不错。\n色彩：申布伦黄\n和黛博拉Terrior一起入的CC的阿铁Chombi水洗，风味走向也是比较传统的水洗瑰夏调性，整体表现和黛博拉Terrior差异不大，从色彩上来说，暖黄的饱和度稍低一些。茉莉花、佛手柑、杏桃、油桃的风味是一如既往，强度也不错，甜感比Terrior稍微逊色一点，酸质显得更突出，偏酸的核果类调性。干净度和柔顺度都是没得说，暖意与雅致的融合。CC的独特风格在这只豆子上仍有体现，但相比起Terrior的香草，这只Chombi更偏什锦糖果一点。\n#记录吧就现在[话题]# #手冲咖啡[话题]# #精品咖啡[话题]# #COTD咖啡探店[话题]# #我的咖啡日记[话题]# #咖啡豆推荐[话题]# #瑰夏[话题]# #咖啡与生活[话题]# #生活美学[话题]# #长沙咖啡店[话题]# #手冲咖啡日常[话题]# #春日[话题]# #咖啡豆[话题]#",
    "body": "豆子：巴拿马-阿尔铁里庄园-Chombi-瑰夏-水洗 from Coffea Circulor\n器具：origami，司令官C40，C壶\n参数：C40-25格，20g粉，粉水比约1:15，水温93摄氏度。\n冲煮：Amis搅拌法：120ml水搅拌焖蒸，25s搅拌，30s静置，下一段松屋式打水至150ml，转中心注水，最后一段大绕圈注至300ml，搅拌，截流，1:58结束萃取，24ml水bypass。\n前嗅觉：高强度花香，有带暖意的甜感，干净度高，浅浅的糖果调，无杂味。\n口感：酸质明亮强度高，甜度具象强度中低，酸更有存在感，黏稠度和重量感都较低，丝滑柔顺，无苦无糙涩。\n后嗅觉：风味强度中高，清晰度不错，甜感强度不算突出，但也容易感知，香气很饱满，经典水洗味，无杂味。\n尾韵：尾韵花果香韧性都不错。\n色彩：申布伦黄\n和黛博拉Terrior一起入的CC的阿铁Chombi水洗，风味走向也是比较传统的水洗瑰夏调性，整体表现和黛博拉Terrior差异不大，从色彩上来说，暖黄的饱和度稍低一些。茉莉花、佛手柑、杏桃、油桃的风味是一如既往，强度也不错，甜感比Terrior稍微逊色一点，酸质显得更突出，偏酸的核果类调性。干净度和柔顺度都是没得说，暖意与雅致的融合。CC的独特风格在这只豆子上仍有体现，但相比起Terrior的香草，这只Chombi更偏什锦糖果一点。",
    "tags": [
      "#记录吧就现在",
      "#手冲咖啡",
      "#精品咖啡",
      "#COTD咖啡探店",
      "#我的咖啡日记",
      "#咖啡豆推荐",
      "#瑰夏",
      "#咖啡与生活",
      "#生活美学",
      "#长沙咖啡店",
      "#手冲咖啡日常",
      "#春日",
      "#咖啡豆"
    ],
    "type": "normal",
    "time": 1743939526000,
    "ipLocation": "",
    "user": {
      "userId": "604eefdd0000000001002980",
      "nickname": "斯慕吉Smoothie"
    },
    "interactInfo": {
      "liked": false,
      "likedCount": "17",
      "collectedCount": "",
      "collected": false,
      "commentCount": "4",
      "sharedCount": ""
    },
    "imageList": [
      {
        "width": 3480,
        "height": 5166,
        "urlDefault": "http://sns-webpic-qc.xhscdn.com/202606302330/d4e7b1a34126531b63fcc9752bae5d36/notes_pre_post/1040g3k031fudccvdg0705o2etveg8ac076der3o!nd_dft_wlteh_webp_3"
      },
      {
        "width": 1179,
        "height": 2013,
        "urlDefault": "http://sns-webpic-qc.xhscdn.com/202606302330/9c6fb039288c4f64a51aef88cb305f91/notes_pre_post/1040g3k031fudccvdg07g5o2etveg8ac0i724jq0!nd_dft_wlteh_webp_3"
      }
    ]
  },
  "comments": [
    {
      "id": "67f66dea0000000020015327",
      "content": "玫瑰真美 是什么品种",
      "likeCount": "0",
      "createTime": 1744203243000,
      "ipLocation": "北京",
      "user": {
        "userId": "61193d5d00000000010053de",
        "nickname": "大哈2kp"
      },
      "subCommentCount": "1",
      "subComments": [
        {
          "id": "67f67173000000001e03dc56",
          "content": "霓裳？哈哈哈哈哈我也不太知道其实",
          "likeCount": "0",
          "createTime": 1744204148000,
          "ipLocation": "湖南",
          "user": {
            "userId": "604eefdd0000000001002980",
            "nickname": "斯慕吉Smoothie"
          },
          "subCommentCount": ""
        }
      ]
    },
    {
      "id": "67f272b6000000001f007c2d",
      "content": "Amis搅拌法需要更新3.0了[派对R]",
      "likeCount": "0",
      "createTime": 1743942326000,
      "ipLocation": "广东",
      "user": {
        "userId": "5b28ef71e8ac2b7caca99b6f",
        "nickname": "Apple"
      },
      "subCommentCount": "1",
      "subComments": [
        {
          "id": "67f27798000000001f006827",
          "content": "[doge]哈哈哈哈可以试试吧，但是牵一发而动全身，其他参数可能都要变",
          "likeCount": "0",
          "createTime": 1743943577000,
          "ipLocation": "湖南",
          "user": {
            "userId": "604eefdd0000000001002980",
            "nickname": "斯慕吉Smoothie"
          },
          "subCommentCount": ""
        }
      ]
    }
  ]
}
