{
  "note": {
    "noteId": "6a2439530000000008027dcc",
    "title": "巧克力测评｜Lindt黑巧85%｜想念野菜生活了",
    "desc": "看了Bacci618，开头就吃巧克力🍫。\n忍不住开冰箱。\n苦能接受，希望大家66大顺睡得好好。\n#黑巧克力[话题]# #每一口都有巧克力[话题]# #可苦可甜[话题]# #瑞士莲[话题]#",
    "body": "看了Bacci618，开头就吃巧克力🍫。\n忍不住开冰箱。\n苦能接受，希望大家66大顺睡得好好。",
    "tags": [
      "#黑巧克力",
      "#每一口都有巧克力",
      "#可苦可甜",
      "#瑞士莲"
    ],
    "type": "normal",
    "time": 1780758867000,
    "ipLocation": "广东",
    "user": {
      "userId": "5b28ef71e8ac2b7caca99b6f",
      "nickname": "Apple"
    },
    "interactInfo": {
      "liked": false,
      "likedCount": "8",
      "collectedCount": "1",
      "collected": false,
      "commentCount": "3",
      "sharedCount": ""
    },
    "imageList": [
      {
        "width": 1920,
        "height": 2560,
        "urlDefault": "http://sns-webpic-qc.xhscdn.com/202606302230/3e9731385167114c2a924dd2b17eed00/notes_pre_post/1040g3k03213244r47e004a6d69nn36rfrq1c1mg!nd_dft_wlteh_webp_3"
      },
      {
        "width": 1920,
        "height": 2560,
        "urlDefault": "http://sns-webpic-qc.xhscdn.com/202606302230/0f5d503f5ee0613e507bd58c80409899/notes_pre_post/1040g3k03213244r47e0g4a6d69nn36rfl33nhho!nd_dft_wlteh_webp_3"
      }
    ]
  },
  "comments": [
    {
      "id": "6a243dd2000000002b0266a4",
      "content": "这个怎样评价这个？",
      "likeCount": "0",
      "createTime": 1780760020000,
      "ipLocation": "广东",
      "user": {
        "userId": "5b28ef71e8ac2b7caca99b6f",
        "nickname": "Apple"
      },
      "subCommentCount": "1",
      "subComments": [
        {
          "id": "6a2468e8000000000d022c00",
          "content": "这个是什么瓜",
          "likeCount": "0",
          "createTime": 1780771048000,
          "ipLocation": "美国",
          "user": {
            "userId": "5c7ce6e1000000001001098e",
            "nickname": "Dont cry峰"
          },
          "subCommentCount": ""
        }
      ]
    },
    {
      "id": "6a244655000000000d021c03",
      "content": "橘子那个好吃",
      "likeCount": "0",
      "createTime": 1780762198000,
      "ipLocation": "美国",
      "user": {
        "userId": "6699acc2000000002401f182",
        "nickname": "BBZ"
      },
      "subCommentCount": "0"
    }
  ]
}
